psycor/__init__.py
psycor/main.py
psycor/commands/add.py
psycor/commands/create.py
psycor/commands/init.py
psycor/commands/install.py
psycor/commands/venv.py
psycor/commands/template/__init__.py
psycor/commands/template/delete.py
psycor/commands/template/save.py
psycor/commands/template/update.py
psycor/templates/fastapi/.gitignore
psycor/templates/fastapi/main.py
psycor/templates/fastapi/psycor.toml
psycor/templates/fastapi/dao/.gitkeep
psycor/templates/fastapi/routers/.gitkeep
psycor/templates/fastapi/schemas/.gitkeep
psycor/templates/fastapi/services/.gitkeep
psycor/templates/flask/.gitignore
psycor/templates/flask/app.py
psycor/templates/flask/models.py
psycor/templates/flask/psycor.toml
psycor/templates/flask/static/.gitkeep
psycor/templates/flask/templates/.gitkeep
psycor/templates/python/.gitignore
psycor/templates/python/README.md
psycor/templates/python/main.py
psycor/templates/python/psycor.toml
psycor-0.1.3.dist-info/METADATA
psycor-0.1.3.dist-info/WHEEL
psycor-0.1.3.dist-info/entry_points.txt
psycor-0.1.3.dist-info/licenses/LICENSE
psycor-0.1.3.dist-info/RECORD
