Metadata-Version: 2.4
Name: psycor
Version: 0.1.3
Summary: CLI tool for Python project scaffolding and environment management
Author: Adrian Obregon
License: MIT License
License-File: LICENSE
Requires-Python: >=3.9
Requires-Dist: click
Requires-Dist: rich
Requires-Dist: rich-click
Requires-Dist: tomli-w
